Metadata-Version: 2.4
Name: textseal
Version: 0.0.4
Summary: Post-hoc LLM watermarking toolkit
Author: Meta Platforms, Inc.
License: MIT License
Project-URL: Repository, https://github.com/facebookresearch/textseal
Keywords: watermarking,llm,language-models,text-generation,contamination-detection
Classifier: Development Status :: 3 - Alpha
Classifier: Intended Audience :: Science/Research
Classifier: License :: OSI Approved :: MIT License
Classifier: Programming Language :: Python :: 3
Classifier: Programming Language :: Python :: 3.11
Classifier: Topic :: Scientific/Engineering :: Artificial Intelligence
Requires-Python: >=3.11
License-File: LICENSE
Requires-Dist: numpy
Requires-Dist: omegaconf
Requires-Dist: msgspec
Requires-Dist: rouge-score
Requires-Dist: sacrebleu
Requires-Dist: sentence-transformers>=3.0.0
Requires-Dist: sentencepiece
Requires-Dist: tiktoken
Requires-Dist: fsspec
Requires-Dist: blobfile
Requires-Dist: scipy
Requires-Dist: orjson
Requires-Dist: torch>=2.0.0
Requires-Dist: transformers>=4.40.0
Requires-Dist: accelerate
Provides-Extra: dev
Requires-Dist: pytest>=7.0; extra == "dev"
Requires-Dist: black; extra == "dev"
Requires-Dist: ruff; extra == "dev"
Provides-Extra: all
Requires-Dist: textseal[dev]; extra == "all"
Dynamic: license-file
